LiaoXuefengSqlJiaocheng/README.md
LiaoXuefengSqlJiaocheng/__init__.py
LiaoXuefengSqlJiaocheng/__main__.py
LiaoXuefengSqlJiaocheng/file.epub
LiaoXuefengSqlJiaocheng/index.html
LiaoXuefengSqlJiaocheng/css/__init__.py
LiaoXuefengSqlJiaocheng/css/annotations.css
LiaoXuefengSqlJiaocheng/css/main.css
LiaoXuefengSqlJiaocheng/css/normalize.css
LiaoXuefengSqlJiaocheng/css/popup.css
LiaoXuefengSqlJiaocheng/font/__init__.py
LiaoXuefengSqlJiaocheng/font/fontello.eot
LiaoXuefengSqlJiaocheng/font/fontello.svg
LiaoXuefengSqlJiaocheng/font/fontello.ttf
LiaoXuefengSqlJiaocheng/font/fontello.woff
LiaoXuefengSqlJiaocheng/img/__init__.py
LiaoXuefengSqlJiaocheng/img/annotator-glyph-sprite.png
LiaoXuefengSqlJiaocheng/img/annotator-icon-sprite.png
LiaoXuefengSqlJiaocheng/img/apple-touch-icon.png
LiaoXuefengSqlJiaocheng/img/cancelfullscreen.png
LiaoXuefengSqlJiaocheng/img/close.png
LiaoXuefengSqlJiaocheng/img/fullscreen.png
LiaoXuefengSqlJiaocheng/img/loader.gif
LiaoXuefengSqlJiaocheng/img/menu-icon.png
LiaoXuefengSqlJiaocheng/img/save.png
LiaoXuefengSqlJiaocheng/img/saved.png
LiaoXuefengSqlJiaocheng/img/settings-s.png
LiaoXuefengSqlJiaocheng/img/settings.png
LiaoXuefengSqlJiaocheng/img/star.png
LiaoXuefengSqlJiaocheng/js/__init__.py
LiaoXuefengSqlJiaocheng/js/epub.js
LiaoXuefengSqlJiaocheng/js/epub.min.js
LiaoXuefengSqlJiaocheng/js/epub.min.map
LiaoXuefengSqlJiaocheng/js/hooks.min.js
LiaoXuefengSqlJiaocheng/js/hooks.min.map
LiaoXuefengSqlJiaocheng/js/reader.js
LiaoXuefengSqlJiaocheng/js/reader.js.map
LiaoXuefengSqlJiaocheng/js/reader.min.js
LiaoXuefengSqlJiaocheng/js/reader.min.map
LiaoXuefengSqlJiaocheng/js/hooks/__init__.py
LiaoXuefengSqlJiaocheng/js/hooks/extensions/__init__.py
LiaoXuefengSqlJiaocheng/js/hooks/extensions/highlight.js
LiaoXuefengSqlJiaocheng/js/libs/__init__.py
LiaoXuefengSqlJiaocheng/js/libs/jquery.min.js
LiaoXuefengSqlJiaocheng/js/libs/localforage.min.js
LiaoXuefengSqlJiaocheng/js/libs/screenfull.js
LiaoXuefengSqlJiaocheng/js/libs/screenfull.min.js
liao_xuefeng_sql_jiaocheng-2024.3.5.0.dist-info/METADATA
liao_xuefeng_sql_jiaocheng-2024.3.5.0.dist-info/WHEEL
liao_xuefeng_sql_jiaocheng-2024.3.5.0.dist-info/entry_points.txt
liao_xuefeng_sql_jiaocheng-2024.3.5.0.dist-info/top_level.txt
liao_xuefeng_sql_jiaocheng-2024.3.5.0.dist-info/RECORD
